{
  "sections": {
    "main": {
      "type": "main-404",
      "settings": {
        "header_404": "<p>404<\/p>",
        "text_404": "<p>Sorry.<br\/><br\/>The page you are looking for cannot be found.<br\/>Please try the links above in our menu or contact us <a href=\"mailto:info@yourmail.com\" title=\"mailto:info@yourmail.com\">info@yourmail.com<\/a>.<\/p><p><a href=\"\/collections\" title=\"All collections\"><em>Continue shopping<\/em><\/a><a href=\"mailto:info@stickerpet.com\"><br\/><\/a><\/p>",
        "image_404": "shopify:\/\/shop_images\/cactus-01.gif"
      }
    }
  },
  "order": [
    "main"
  ]
}
