{
  "sections": {
    "1637853061f1d0b879": {
      "type": "product-main",
      "blocks": {
        "0c2485e1-0303-4c9b-8b21-5178b87a9600": {
          "type": "quantity_selector",
          "settings": {
          }
        },
        "0423df30-6c9c-4185-87bf-9c971a1fe15f": {
          "type": "buy_buttons",
          "settings": {
            "show_dynamic_checkout": true
          }
        },
        "c0774ad9-7bd9-46fd-b5f5-9183314d815e": {
          "type": "title",
          "settings": {
          }
        },
        "9fd487a2-0e68-4742-b724-388ed9f241a0": {
          "type": "price",
          "settings": {
          }
        },
        "c292310d-a365-49e3-bebd-c7a876cd432d": {
          "type": "text",
          "settings": {
            "text": "{{ product.vendor }}",
            "text_style": "uppercase"
          }
        },
        "bbc2966d-b263-4b2f-89ed-3bd970987f31": {
          "type": "description",
          "settings": {
          }
        }
      },
      "block_order": [
        "0c2485e1-0303-4c9b-8b21-5178b87a9600",
        "0423df30-6c9c-4185-87bf-9c971a1fe15f",
        "c0774ad9-7bd9-46fd-b5f5-9183314d815e",
        "9fd487a2-0e68-4742-b724-388ed9f241a0",
        "c292310d-a365-49e3-bebd-c7a876cd432d",
        "bbc2966d-b263-4b2f-89ed-3bd970987f31"
      ],
      "settings": {
        "product_section_type": "default",
        "product_main_color_scheme": "background-4"
      }
    },
    "16290966851973846b": {
      "type": "product-quality",
      "blocks": {
        "9f072f77-f73e-4a9d-b687-74dded20d9b5": {
          "type": "quality_block",
          "settings": {
            "heading": "🔫 sticker<br> proof",
            "hide_block": false
          }
        },
        "7ab40d95-4af7-485e-8f26-4d010fe2c9d1": {
          "type": "quality_block",
          "settings": {
            "heading": "super 🦎<br>\nsticky",
            "hide_block": false
          }
        }
      },
      "block_order": [
        "9f072f77-f73e-4a9d-b687-74dded20d9b5",
        "7ab40d95-4af7-485e-8f26-4d010fe2c9d1"
      ],
      "settings": {
        "product_quality_color_scheme": "background-3"
      }
    },
    "162909679183423fb6": {
      "type": "product-perks",
      "blocks": {
        "a0a25cf3-33d8-4c00-a941-b335613f1baf": {
          "type": "perk",
          "settings": {
            "perk_image": "shopify:\/\/shop_images\/noun_Card_2555057.png",
            "perk_text": "Secure checkout"
          }
        },
        "ea37f555-d14f-443d-8b18-1a82ca6e829e": {
          "type": "perk",
          "settings": {
            "perk_image": "shopify:\/\/shop_images\/noun_Gift_2555021_1.png",
            "perk_text": "Gifting options"
          }
        },
        "1ec403ef-5039-4556-80c9-2301c3ddd6e5": {
          "type": "perk",
          "settings": {
            "perk_image": "shopify:\/\/shop_images\/noun_Mail_2555061.png",
            "perk_text": "Fits in your mailbox"
          }
        },
        "e27177ca-fb86-4aaf-be3a-84ce6d7d8ecb": {
          "type": "perk",
          "settings": {
            "perk_image": "shopify:\/\/shop_images\/noun_typing_2555043.png",
            "perk_text": "Super fast answers"
          }
        }
      },
      "block_order": [
        "a0a25cf3-33d8-4c00-a941-b335613f1baf",
        "ea37f555-d14f-443d-8b18-1a82ca6e829e",
        "1ec403ef-5039-4556-80c9-2301c3ddd6e5",
        "e27177ca-fb86-4aaf-be3a-84ce6d7d8ecb"
      ],
      "settings": {
      }
    },
    "16382829904a479123": {
      "type": "product-recommendations",
      "settings": {
        "heading": "You may also like",
        "image_ratio": "adapt",
        "show_secondary_image": true,
        "add_image_padding": true,
        "show_vendor": true
      }
    }
  },
  "order": [
    "1637853061f1d0b879",
    "16290966851973846b",
    "162909679183423fb6",
    "16382829904a479123"
  ]
}
